praetorian_cli/__init__.py
praetorian_cli/main.py
praetorian_cli/handlers/__init__.py
praetorian_cli/handlers/add.py
praetorian_cli/handlers/aegis.py
praetorian_cli/handlers/agent.py
praetorian_cli/handlers/chariot.py
praetorian_cli/handlers/cli_decorators.py
praetorian_cli/handlers/configure.py
praetorian_cli/handlers/delete.py
praetorian_cli/handlers/enrich.py
praetorian_cli/handlers/get.py
praetorian_cli/handlers/imports.py
praetorian_cli/handlers/link.py
praetorian_cli/handlers/list.py
praetorian_cli/handlers/script.py
praetorian_cli/handlers/search.py
praetorian_cli/handlers/ssh_utils.py
praetorian_cli/handlers/test.py
praetorian_cli/handlers/unlink.py
praetorian_cli/handlers/update.py
praetorian_cli/handlers/utils.py
praetorian_cli/scripts/__init__.py
praetorian_cli/scripts/utils.py
praetorian_cli/scripts/commands/__init__.py
praetorian_cli/scripts/commands/nmap-example.py
praetorian_cli/sdk/__init__.py
praetorian_cli/sdk/chariot.py
praetorian_cli/sdk/keychain.py
praetorian_cli/sdk/mcp_server.py
praetorian_cli/sdk/entities/__init__.py
praetorian_cli/sdk/entities/accounts.py
praetorian_cli/sdk/entities/aegis.py
praetorian_cli/sdk/entities/agents.py
praetorian_cli/sdk/entities/assets.py
praetorian_cli/sdk/entities/attributes.py
praetorian_cli/sdk/entities/capabilities.py
praetorian_cli/sdk/entities/configurations.py
praetorian_cli/sdk/entities/credentials.py
praetorian_cli/sdk/entities/definitions.py
praetorian_cli/sdk/entities/files.py
praetorian_cli/sdk/entities/integrations.py
praetorian_cli/sdk/entities/jobs.py
praetorian_cli/sdk/entities/keys.py
praetorian_cli/sdk/entities/preseeds.py
praetorian_cli/sdk/entities/risks.py
praetorian_cli/sdk/entities/scanners.py
praetorian_cli/sdk/entities/schema.py
praetorian_cli/sdk/entities/search.py
praetorian_cli/sdk/entities/seeds.py
praetorian_cli/sdk/entities/settings.py
praetorian_cli/sdk/entities/statistics.py
praetorian_cli/sdk/entities/webhook.py
praetorian_cli/sdk/entities/webpage.py
praetorian_cli-2.2.17.dist-info/licenses/LICENSE
praetorian_cli-2.2.17.dist-info/METADATA
praetorian_cli-2.2.17.dist-info/WHEEL
praetorian_cli-2.2.17.dist-info/entry_points.txt
praetorian_cli-2.2.17.dist-info/top_level.txt
praetorian_cli-2.2.17.dist-info/RECORD
