Metadata-Version: 2.4
Name: praetorian-cli
Version: 2.2.17
Summary: For interacting with the Chariot API
Home-page: https://github.com/praetorian-inc/praetorian-cli
Author: Praetorian
Author-email: support@praetorian.com
Classifier: Programming Language :: Python :: 3
Classifier: License :: OSI Approved :: MIT License
Classifier: Operating System :: OS Independent
Requires-Python: >=3.10
License-File: LICENSE
Requires-Dist: click>=8.1.7
Requires-Dist: boto3>=1.34.0
Requires-Dist: requests>=2.31.0
Requires-Dist: pytest>=8.0.2
Requires-Dist: mcp>=1.12.2
Requires-Dist: anyio>=3.0.0
Requires-Dist: textual>=0.47.0
Requires-Dist: rich>=13.0.0
Requires-Dist: prompt_toolkit>=3.0.0
Dynamic: license-file
